{
    "sourceFile": "src/main/electron/events/onSendToRender.ts",
    "activeCommit": 0,
    "commits": [
        {
            "activePatchIndex": 11,
            "patches": [
                {
                    "date": 1665989999429,
                    "content": "Index: \n===================================================================\n--- \n+++ \n"
                },
                {
                    "date": 1665991296459,
                    "content": "Index: \n===================================================================\n--- \n+++ \n@@ -1,5 +0,0 @@\n-import { BrowserWindow } from \"electron\";\n-\n-export const onSendToRender = (window:BrowserWindow) => {\n-    \n-}\n\\ No newline at end of file\n"
                },
                {
                    "date": 1665991330407,
                    "content": "Index: \n===================================================================\n--- \n+++ \n@@ -0,0 +1,5 @@\n+\n+\n+export const onSendToRender = () => {\n+    \n+}\n\\ No newline at end of file\n"
                },
                {
                    "date": 1665992694974,
                    "content": "Index: \n===================================================================\n--- \n+++ \n@@ -1,5 +1,11 @@\n+import { BrowserWindow } from \"electron\"\n+import { readFileSync } from \"fs\"\n+import { OPEN_NEW_FILE } from \"./constant\"\n \n-\n\\ No newline at end of file\n-export const onSendToRender = () => {\n-    \n-}\n+export const openNewFile = (filePath: string, window: BrowserWindow) => {\n+    const fileContent = readFileSync(filePath, 'utf-8')\n+    window.webContents.send(OPEN_NEW_FILE, {\n+      filePath,\n+      fileContent\n+    })\n+  }\n\\ No newline at end of file\n"
                },
                {
                    "date": 1665992721399,
                    "content": "Index: \n===================================================================\n--- \n+++ \n@@ -1,9 +1,9 @@\n import { BrowserWindow } from \"electron\"\n import { readFileSync } from \"fs\"\n import { OPEN_NEW_FILE } from \"./constant\"\n \n-export const openNewFile = (filePath: string, window: BrowserWindow) => {\n+export const clickOpenFile = (filePath: string, window: BrowserWindow) => {\n     const fileContent = readFileSync(filePath, 'utf-8')\n     window.webContents.send(OPEN_NEW_FILE, {\n       filePath,\n       fileContent\n"
                },
                {
                    "date": 1665992814151,
                    "content": "Index: \n===================================================================\n--- \n+++ \n@@ -1,9 +1,9 @@\n import { BrowserWindow } from \"electron\"\n import { readFileSync } from \"fs\"\n import { OPEN_NEW_FILE } from \"./constant\"\n \n-export const clickOpenFile = (filePath: string, window: BrowserWindow) => {\n+export const openNewFile = (filePath: string, window: BrowserWindow) => {\n     const fileContent = readFileSync(filePath, 'utf-8')\n     window.webContents.send(OPEN_NEW_FILE, {\n       filePath,\n       fileContent\n"
                },
                {
                    "date": 1665993746762,
                    "content": "Index: \n===================================================================\n--- \n+++ \n@@ -2,8 +2,9 @@\n import { readFileSync } from \"fs\"\n import { OPEN_NEW_FILE } from \"./constant\"\n \n export const openNewFile = (filePath: string, window: BrowserWindow) => {\n+    console.log(filePath)\n     const fileContent = readFileSync(filePath, 'utf-8')\n     window.webContents.send(OPEN_NEW_FILE, {\n       filePath,\n       fileContent\n"
                },
                {
                    "date": 1665994042883,
                    "content": "Index: \n===================================================================\n--- \n+++ \n@@ -2,9 +2,8 @@\n import { readFileSync } from \"fs\"\n import { OPEN_NEW_FILE } from \"./constant\"\n \n export const openNewFile = (filePath: string, window: BrowserWindow) => {\n-    console.log(filePath)\n     const fileContent = readFileSync(filePath, 'utf-8')\n     window.webContents.send(OPEN_NEW_FILE, {\n       filePath,\n       fileContent\n"
                },
                {
                    "date": 1666058350800,
                    "content": "Index: \n===================================================================\n--- \n+++ \n@@ -3,8 +3,9 @@\n import { OPEN_NEW_FILE } from \"./constant\"\n \n export const openNewFile = (filePath: string, window: BrowserWindow) => {\n     const fileContent = readFileSync(filePath, 'utf-8')\n+    console.log('main listener openNewFile')\n     window.webContents.send(OPEN_NEW_FILE, {\n       filePath,\n       fileContent\n     })\n"
                },
                {
                    "date": 1666058369589,
                    "content": "Index: \n===================================================================\n--- \n+++ \n@@ -3,9 +3,8 @@\n import { OPEN_NEW_FILE } from \"./constant\"\n \n export const openNewFile = (filePath: string, window: BrowserWindow) => {\n     const fileContent = readFileSync(filePath, 'utf-8')\n-    console.log('main listener openNewFile')\n     window.webContents.send(OPEN_NEW_FILE, {\n       filePath,\n       fileContent\n     })\n"
                },
                {
                    "date": 1666531744141,
                    "content": "Index: \n===================================================================\n--- \n+++ \n@@ -1,11 +1,12 @@\n-import { BrowserWindow } from \"electron\"\n-import { readFileSync } from \"fs\"\n-import { OPEN_NEW_FILE } from \"./constant\"\n+import { BrowserWindow } from 'electron'\n+import { readFileSync } from 'fs'\n+import { OPEN_NEW_FILE } from './constant'\n \n export const openNewFile = (filePath: string, window: BrowserWindow) => {\n-    const fileContent = readFileSync(filePath, 'utf-8')\n-    window.webContents.send(OPEN_NEW_FILE, {\n-      filePath,\n\\ No newline at end of file\n-      fileContent\n-    })\n-  }\n+  const fileContent = readFileSync(filePath, 'utf-8')\n+  window.webContents.send(OPEN_NEW_FILE, {\n+    filePath,\n+    fileContent\n+  })\n+}\n+export const \n\\ No newline at end of file\n"
                },
                {
                    "date": 1666532142897,
                    "content": "Index: \n===================================================================\n--- \n+++ \n@@ -1,12 +1,14 @@\n import { BrowserWindow } from 'electron'\n import { readFileSync } from 'fs'\n-import { OPEN_NEW_FILE } from './constant'\n+import { OPEN_NEW_FILE, UPDATE_FILE_LIST } from './constant'\n \n export const openNewFile = (filePath: string, window: BrowserWindow) => {\n   const fileContent = readFileSync(filePath, 'utf-8')\n   window.webContents.send(OPEN_NEW_FILE, {\n     filePath,\n     fileContent\n   })\n }\n\\ No newline at end of file\n-export const \n+export const updateFileList = (window:BrowserWindow) =>{\n+  window.webContents.send(UPDATE_FILE_LIST)\n+}\n\\ No newline at end of file\n"
                }
            ],
            "date": 1665989999429,
            "name": "Commit-0",
            "content": "import { BrowserWindow } from \"electron\";\n\nexport const onSendToRender = (window:BrowserWindow) => {\n    \n}"
        }
    ]
}